{
  "name": "Adversarial Network Game - Multi-path Enterprise",
  "description": "Human Hacker chooses Move/Scan/Attack while AI Defender reacts with Minimax, Alpha-Beta or Expectimax on a larger multi-path network.",
  "hacker_start": "PC1",
  "goal_nodes": ["Server", "Database"],
  "nodes": [
    {"id": "PC1", "kind": "pc", "position": [70, 190], "security_level": 1, "zone": "User Zone", "blocked": false, "visible": true, "compromised": true, "monitored": false, "importance": 3, "detection_risk": 0.0},
    {"id": "PC2", "kind": "pc", "position": [70, 530], "security_level": 2, "zone": "User Zone", "blocked": false, "visible": true, "compromised": false, "monitored": false, "importance": 3, "detection_risk": 0.1},
    {"id": "Gateway", "kind": "router", "position": [240, 210], "security_level": 3, "zone": "Edge", "blocked": false, "visible": true, "compromised": false, "monitored": false, "importance": 5, "detection_risk": 0.2},
    {"id": "VPN", "kind": "router", "position": [240, 520], "security_level": 4, "zone": "Remote Access", "blocked": false, "visible": true, "compromised": false, "monitored": true, "importance": 6, "detection_risk": 0.4},
    {"id": "DMZ_A", "kind": "switch", "position": [430, 110], "security_level": 4, "zone": "DMZ", "blocked": false, "visible": true, "compromised": false, "monitored": false, "importance": 5, "detection_risk": 0.2},
    {"id": "DMZ_B", "kind": "switch", "position": [430, 325], "security_level": 4, "zone": "DMZ", "blocked": false, "visible": true, "compromised": false, "monitored": false, "importance": 5, "detection_risk": 0.2},
    {"id": "CloudGW", "kind": "router", "position": [430, 630], "security_level": 5, "zone": "Cloud Edge", "blocked": false, "visible": true, "compromised": false, "monitored": true, "importance": 6, "detection_risk": 0.5},
    {"id": "IDS_A", "kind": "ids", "position": [650, 215], "security_level": 7, "zone": "Monitoring", "blocked": false, "visible": true, "compromised": false, "monitored": true, "importance": 8, "detection_risk": 0.9},
    {"id": "IDS_B", "kind": "ids", "position": [650, 525], "security_level": 7, "zone": "Monitoring", "blocked": false, "visible": true, "compromised": false, "monitored": true, "importance": 8, "detection_risk": 0.85},
    {"id": "Proxy", "kind": "router", "position": [880, 110], "security_level": 6, "zone": "Service Edge", "blocked": false, "visible": true, "compromised": false, "monitored": true, "importance": 7, "detection_risk": 0.5},
    {"id": "FirewallA", "kind": "firewall", "position": [880, 335], "security_level": 8, "zone": "Server Zone", "blocked": false, "visible": true, "compromised": false, "monitored": true, "importance": 9, "detection_risk": 0.6},
    {"id": "FirewallB", "kind": "firewall", "position": [880, 610], "security_level": 8, "zone": "Server Zone", "blocked": false, "visible": true, "compromised": false, "monitored": true, "importance": 9, "detection_risk": 0.65},
    {"id": "AppServer", "kind": "server", "position": [1110, 110], "security_level": 8, "zone": "App Zone", "blocked": false, "visible": true, "compromised": false, "monitored": true, "importance": 9, "detection_risk": 0.8},
    {"id": "Server", "kind": "server", "position": [1160, 335], "security_level": 10, "zone": "Server Zone", "blocked": false, "visible": true, "compromised": false, "monitored": true, "importance": 10, "detection_risk": 1.0},
    {"id": "Database", "kind": "database", "position": [1160, 610], "security_level": 10, "zone": "Data Zone", "blocked": false, "visible": true, "compromised": false, "monitored": true, "importance": 10, "detection_risk": 1.0},
    {"id": "BackupDB", "kind": "database", "position": [1110, 745], "security_level": 9, "zone": "Backup Zone", "blocked": false, "visible": true, "compromised": false, "monitored": true, "importance": 8, "detection_risk": 0.9}
  ],
  "edges": [
    {"source": "PC1", "target": "Gateway", "base_cost": 1.0, "blocked": false, "bidirectional": true},
    {"source": "PC1", "target": "PC2", "base_cost": 1.2, "blocked": false, "bidirectional": true},
    {"source": "PC2", "target": "VPN", "base_cost": 1.0, "blocked": false, "bidirectional": true},
    {"source": "Gateway", "target": "VPN", "base_cost": 1.4, "blocked": false, "bidirectional": true},
    {"source": "Gateway", "target": "DMZ_A", "base_cost": 1.0, "blocked": false, "bidirectional": true},
    {"source": "Gateway", "target": "DMZ_B", "base_cost": 1.0, "blocked": false, "bidirectional": true},
    {"source": "VPN", "target": "CloudGW", "base_cost": 1.2, "blocked": false, "bidirectional": true},
    {"source": "VPN", "target": "DMZ_B", "base_cost": 1.3, "blocked": false, "bidirectional": true},
    {"source": "DMZ_A", "target": "DMZ_B", "base_cost": 1.1, "blocked": false, "bidirectional": true},
    {"source": "DMZ_A", "target": "IDS_A", "base_cost": 1.0, "blocked": false, "bidirectional": true},
    {"source": "DMZ_B", "target": "IDS_A", "base_cost": 1.2, "blocked": false, "bidirectional": true},
    {"source": "DMZ_B", "target": "IDS_B", "base_cost": 1.0, "blocked": false, "bidirectional": true},
    {"source": "CloudGW", "target": "IDS_B", "base_cost": 1.0, "blocked": false, "bidirectional": true},
    {"source": "IDS_A", "target": "IDS_B", "base_cost": 1.4, "blocked": false, "bidirectional": true},
    {"source": "IDS_A", "target": "Proxy", "base_cost": 1.0, "blocked": false, "bidirectional": true},
    {"source": "IDS_A", "target": "FirewallA", "base_cost": 1.0, "blocked": false, "bidirectional": true},
    {"source": "IDS_B", "target": "FirewallB", "base_cost": 1.0, "blocked": false, "bidirectional": true},
    {"source": "Proxy", "target": "AppServer", "base_cost": 1.2, "blocked": false, "bidirectional": true},
    {"source": "Proxy", "target": "FirewallA", "base_cost": 1.4, "blocked": false, "bidirectional": true},
    {"source": "FirewallA", "target": "AppServer", "base_cost": 1.0, "blocked": false, "bidirectional": true},
    {"source": "FirewallA", "target": "Server", "base_cost": 1.0, "blocked": false, "bidirectional": true},
    {"source": "FirewallA", "target": "FirewallB", "base_cost": 1.3, "blocked": false, "bidirectional": true},
    {"source": "Server", "target": "Database", "base_cost": 1.2, "blocked": false, "bidirectional": true},
    {"source": "FirewallB", "target": "Server", "base_cost": 1.4, "blocked": false, "bidirectional": true},
    {"source": "FirewallB", "target": "Database", "base_cost": 1.0, "blocked": false, "bidirectional": true},
    {"source": "FirewallB", "target": "BackupDB", "base_cost": 1.2, "blocked": false, "bidirectional": true},
    {"source": "AppServer", "target": "Server", "base_cost": 1.0, "blocked": false, "bidirectional": true},
    {"source": "Database", "target": "BackupDB", "base_cost": 1.0, "blocked": false, "bidirectional": true}
  ],
  "metadata": {
    "group": "adversarial",
    "max_turns": 14,
    "ids_detect_prob": 0.7,
    "firewall_block_prob": 0.8,
    "notes": "Larger adversarial map with redundant DMZ, VPN, cloud, IDS and firewall paths. Edge colors show attacker movement and defender response."
  }
}
